MANIFEST.in
README.md
setup.py
pyrddl/__init__.py
pyrddl/cpf.py
pyrddl/domain.py
pyrddl/expr.py
pyrddl/instance.py
pyrddl/nonfluents.py
pyrddl/parser.py
pyrddl/parsetab.py
pyrddl/pvariable.py
pyrddl/rddl.py
pyrddl/utils.py
pyrddl.egg-info/PKG-INFO
pyrddl.egg-info/SOURCES.txt
pyrddl.egg-info/dependency_links.txt
pyrddl.egg-info/not-zip-safe
pyrddl.egg-info/requires.txt
pyrddl.egg-info/top_level.txt
rddl/Mars_Rover.rddl
rddl/Navigation.rddl
rddl/Reservoir.rddl
scripts/pyrddl