Metadata-Version: 1.1
Name: pyrddl
Version: 0.1.8
Summary: RDDL lexer/parser in Python3.
Home-page: https://github.com/thiagopbueno/pyrddl
Author: Thiago P. Bueno
Author-email: thiago.pbueno@gmail.com
License: GNU General Public License v3.0
Keywords: rddl,parser,mdp,dbn
Platform: UNKNOWN
Classifier: Development Status :: 3 - Alpha
Classifier: Environment :: Console
Classifier: Intended Audience :: Science/Research
Classifier: License :: OSI Approved :: GNU General Public License v3 (GPLv3)
Classifier: Natural Language :: English
Classifier: Operating System :: OS Independent
Classifier: Programming Language :: Python :: 3
Classifier: Topic :: Scientific/Engineering :: Artificial Intelligence
